pycut/__init__.py
pycut/cli.py
pycut/pycut.py
pycut-0.9.0.dist-info/AUTHORS.rst
pycut-0.9.0.dist-info/LICENSE
pycut-0.9.0.dist-info/METADATA
pycut-0.9.0.dist-info/WHEEL
pycut-0.9.0.dist-info/entry_points.txt
pycut-0.9.0.dist-info/top_level.txt
pycut-0.9.0.dist-info/RECORD
