Metadata-Version: 2.1
Name: pycut
Version: 0.9.0
Summary: PyCut
Home-page: https://github.com/gmagno/pycut
Author: Goncalo
Author-email: goncalo@gmagno.dev
License: MIT license
Keywords: pycut
Platform: UNKNOWN
Classifier: Development Status :: 2 - Pre-Alpha
Classifier: Intended Audience :: Developers
Classifier: License :: OSI Approved :: MIT License
Classifier: Natural Language :: English
Classifier: Programming Language :: Python :: 3
Classifier: Programming Language :: Python :: 3.5
Classifier: Programming Language :: Python :: 3.6
Classifier: Programming Language :: Python :: 3.7
Classifier: Programming Language :: Python :: 3.8
Requires-Python: >=3.5
